{
    "frames": 2168,
    "file_name": "seq7.avi",
    "0": {
        "shake_id": 0,
        "bounding_box": {
            "rectangles": [
                [
                    207.0,
                    236.0,
                    239.0,
                    259.0
                ],
                [
                    206.5,
                    238.25,
                    238.5,
                    261.25
                ],
                [
                    206.0,
                    240.5,
                    238.0,
                    263.5
                ],
                [
                    206.5,
                    243.5,
                    238.5,
                    266.5
                ],
                [
                    207.0,
                    246.5,
                    239.0,
                    269.5
                ],
                [
                    208.0,
                    243.25,
                    240.0,
                    266.25
                ],
                [
                    209.0,
                    240.0,
                    241.0,
                    263.0
                ],
                [
                    211.0,
                    233.0,
                    243.0,
                    256.0
                ],
                [
                    211.0,
                    226.5,
                    243.0,
                    249.5
                ],
                [
                    210.125,
                    229.75,
                    242.125,
                    252.75
                ],
                [
                    209.25,
                    233.0,
                    241.25,
                    256.0
                ],
                [
                    208.375,
                    236.25,
                    240.375,
                    259.25
                ],
                [
                    207.5,
                    239.5,
                    239.5,
                    262.5
                ],
                [
                    207.375,
                    237.625,
                    239.375,
                    260.625
                ],
                [
                    207.25,
                    235.75,
                    239.25,
                    258.75
                ],
                [
                    207.125,
                    233.875,
                    239.125,
                    256.875
                ],
                [
                    207.0,
                    232.0,
                    239.0,
                    255.0
                ],
                [
                    207.66666666666666,
                    234.33333333333334,
                    239.66666666666666,
                    257.33333333333337
                ],
                [
                    208.33333333333334,
                    236.66666666666666,
                    240.33333333333334,
                    259.66666666666663
                ],
                [
                    209.0,
                    239.0,
                    241.0,
                    262.0
                ],
                [
                    210.5,
                    245.0,
                    242.5,
                    268.0
                ],
                [
                    205.5,
                    245.5,
                    237.5,
                    268.5
                ],
                [
                    206.25,
                    241.5,
                    238.25,
                    264.5
                ],
                [
                    207.0,
                    237.5,
                    239.0,
                    260.5
                ],
                [
                    206.0,
                    229.5,
                    238.0,
                    252.5
                ],
                [
                    207.0,
                    222.5,
                    239.0,
                    245.5
                ],
                [
                    206.0,
                    226.5,
                    238.0,
                    249.5
                ],
                [
                    205.0,
                    230.5,
                    237.0,
                    253.5
                ],
                [
                    205.5,
                    236.0,
                    237.5,
                    259.0
                ],
                [
                    206.0,
                    241.5,
                    238.0,
                    264.5
                ],
                [
                    206.83333333333334,
                    238.0,
                    238.83333333333334,
                    261.0
                ],
                [
                    207.66666666666666,
                    234.5,
                    239.66666666666666,
                    257.5
                ],
                [
                    208.5,
                    231.0,
                    240.5,
                    254.0
                ],
                [
                    208.875,
                    234.0,
                    240.875,
                    257.0
                ],
                [
                    209.25,
                    237.0,
                    241.25,
                    260.0
                ],
                [
                    209.625,
                    240.0,
                    241.625,
                    263.0
                ],
                [
                    210.0,
                    243.0,
                    242.0,
                    266.0
                ],
                [
                    210.4,
                    242.1,
                    242.4,
                    265.1
                ],
                [
                    210.8,
                    241.2,
                    242.8,
                    264.2
                ],
                [
                    211.2,
                    240.3,
                    243.2,
                    263.3
                ],
                [
                    211.6,
                    239.4,
                    243.6,
                    262.4
                ],
                [
                    212.0,
                    238.5,
                    244.0,
                    261.5
                ],
                [
                    212.0,
                    238.5,
                    244.0,
                    261.5
                ],
                [
                    212.0,
                    238.5,
                    244.0,
                    261.5
                ],
                [
                    212.0,
                    238.5,
                    244.0,
                    261.5
                ],
                [
                    212.0,
                    238.5,
                    244.0,
                    261.5
                ],
                [
                    212.0,
                    238.5,
                    244.0,
                    261.5
                ],
                [
                    212.0,
                    238.5,
                    244.0,
                    261.5
                ],
                [
                    212.0,
                    238.5,
                    244.0,
                    261.5
                ],
                [
                    212.0,
                    238.5,
                    244.0,
                    261.5
                ],
                [
                    212.0,
                    238.5,
                    244.0,
                    261.5
                ],
                [
                    212.0,
                    238.5,
                    244.0,
                    261.5
                ],
                [
                    212.0,
                    238.5,
                    244.0,
                    261.5
                ],
                [
                    212.0,
                    238.5,
                    244.0,
                    261.5
                ]
            ],
            "marked_points": [
                820,
                822,
                824,
                826,
                827,
                828,
                832,
                836,
                839,
                840,
                841,
                843,
                844,
                845,
                847,
                849,
                852,
                856,
                861,
                873
            ]
        }
    }
}